[
  {
    "id": "1",
    "authors": "C Cirillo, MAG Matarrese, E Monda, ME Pagnano, J Vitale, F Verrillo, ...",
    "title": "Artificial intelligence for left ventricular hypertrophy detection and differentiation on echocardiography, cardiac magnetic resonance and cardiac computed tomography: A …",
    "journal": "International Journal of Cardiology 422",
    "year": "2025",
    "scholarLink": "https://scholar.google.com/citations?view_op=view_citation&hl=en&user=HnOZ1UUAAAAJ&pagesize=100&citation_for_view=HnOZ1UUAAAAJ:2osOgNQ5qMEC"
  }
]
